LICENSE
MANIFEST.in
README.rst
pyproject.toml
setup.cfg
setup.py
django_drf_blog_api/__init__.py
django_drf_blog_api/admin.py
django_drf_blog_api/apps.py
django_drf_blog_api/models.py
django_drf_blog_api/serializer.py
django_drf_blog_api/signals.py
django_drf_blog_api/tests.py
django_drf_blog_api/urls.py
django_drf_blog_api/utils.py
django_drf_blog_api/views.py
django_drf_blog_api.egg-info/PKG-INFO
django_drf_blog_api.egg-info/SOURCES.txt
django_drf_blog_api.egg-info/dependency_links.txt
django_drf_blog_api.egg-info/requires.txt
django_drf_blog_api.egg-info/top_level.txt
django_drf_blog_api/migrations/__init__.py